transperegrina/__init__.py
transperegrina/email_class.py
transperegrina/email_sender.py
transperegrina/sql.py
transperegrina/sql_dw.py
transperegrina/ultima_data.py
transperegrina/whatsapp.py
transperegrina-0.1.41.dist-info/METADATA
transperegrina-0.1.41.dist-info/WHEEL
transperegrina-0.1.41.dist-info/RECORD
