Metadata-Version: 2.3
Name: transperegrina
Version: 0.1.41
Summary: 
Author: Ronaldo da Rocha
Author-email: ronaldo.rocha.jimmy@gmail.com
Requires-Python: >=3.10
Classifier: Programming Language :: Python :: 3
Classifier: Programming Language :: Python :: 3.10
Classifier: Programming Language :: Python :: 3.11
Classifier: Programming Language :: Python :: 3.12
Classifier: Programming Language :: Python :: 3.13
